chessidle/__init__.py
chessidle/__main__.py
chessidle/bench.py
chessidle/bitboard.py
chessidle/engine.py
chessidle/evaluation.py
chessidle/history.py
chessidle/limits.py
chessidle/main.py
chessidle/move.py
chessidle/move_generation.py
chessidle/move_pick.py
chessidle/nnue.py
chessidle/nnue_weights.py
chessidle/options.py
chessidle/piece.py
chessidle/polyglot.py
chessidle/position.py
chessidle/search.py
chessidle/see.py
chessidle/square.py
chessidle/transposition.py
chessidle/tune.py
chessidle/uci.py
chessidle-1.3.0.dist-info/LICENSE
chessidle-1.3.0.dist-info/METADATA
chessidle-1.3.0.dist-info/WHEEL
chessidle-1.3.0.dist-info/entry_points.txt
chessidle-1.3.0.dist-info/top_level.txt
chessidle-1.3.0.dist-info/RECORD
