Metadata-Version: 2.2
Name: chessidle
Version: 1.3.0
Summary: Python chess engine
Author: Alvin Peng
License:                     GNU GENERAL PUBLIC LICENSE
Project-URL: Homepage, https://github.com/alvinypeng/chessidle
Keywords: chess,engine,bot,ai,uci
Classifier: Intended Audience :: Developers
Classifier: Intended Audience :: Science/Research
Classifier: License :: OSI Approved :: GNU General Public License v3 (GPLv3)
Classifier: Operating System :: OS Independent
Classifier: Programming Language :: Python :: 3
Classifier: Topic :: Games/Entertainment :: Board Games
Classifier: Topic :: Games/Entertainment :: Turn Based Strategy
Requires-Python: >=3.9
License-File: LICENSE
Provides-Extra: numpy
Requires-Dist: numpy; extra == "numpy"
